nonebot_plugin_hyp/__init__.py
nonebot_plugin_hyp/api.py
nonebot_plugin_hyp/datebase.py
nonebot_plugin_hyp/handle.py
nonebot_plugin_hyp/message.py
nonebot_plugin_hyp/utils.py
nonebot_plugin_hyp-0.0.4.dist-info/LICENSE
nonebot_plugin_hyp-0.0.4.dist-info/METADATA
nonebot_plugin_hyp-0.0.4.dist-info/WHEEL
nonebot_plugin_hyp-0.0.4.dist-info/RECORD
