Metadata-Version: 2.1
Name: nonebot-plugin-hyp
Version: 0.0.4
Summary: 一款旨在查询全球最大的小游戏服务器'Hypixel'玩家游戏数据信息及Minecraft-Mojang数据的插件
Home-page: https://github.com/Reversedeer/nonebot_plugin_hyp
License: MIT
Author: Reversedeer
Requires-Python: >=3.9,<4.0
Classifier: License :: OSI Approved :: MIT License
Classifier: Programming Language :: Python :: 3
Classifier: Programming Language :: Python :: 3.9
Classifier: Programming Language :: Python :: 3.10
Classifier: Programming Language :: Python :: 3.11
Classifier: Programming Language :: Python :: 3.12
Classifier: Programming Language :: Python :: 3.13
Requires-Dist: httpx (>=0.23.1,<0.24.0)
Requires-Dist: nonebot-adapter-onebot (>=2.1.3,<3.0.0)
Requires-Dist: nonebot2 (>=2.2.0,<3.0.0)
Requires-Dist: pydantic (>=1.10.0,<3.0.0,!=2.5.0,!=2.5.1,!=2.10.0)
Project-URL: Repository, https://github.com/Reversedeer/nonebot_plugin_hyp
